kogito/__init__.py
kogito/core/__init__.py
kogito/core/callbacks.py
kogito/core/dataset.py
kogito/core/head.py
kogito/core/knowledge.py
kogito/core/model.py
kogito/core/processors/__init__.py
kogito/core/processors/data/vocab_glove_100d.npy
kogito/core/processors/head.py
kogito/core/processors/models/__init__.py
kogito/core/processors/models/bert.py
kogito/core/processors/models/distilbert.py
kogito/core/processors/models/swem.py
kogito/core/processors/models/utils.py
kogito/core/processors/relation.py
kogito/core/relation.py
kogito/core/utils.py
kogito/evaluation/LICENSE
kogito/evaluation/__init__.py
kogito/evaluation/bert_score/__init__.py
kogito/evaluation/bert_score/bert_score.py
kogito/evaluation/bert_score/score.py
kogito/evaluation/bert_score/utils.py
kogito/evaluation/bleu/.gitignore
kogito/evaluation/bleu/LICENSE
kogito/evaluation/bleu/__init__.py
kogito/evaluation/bleu/bleu.py
kogito/evaluation/bleu/bleu_scorer.py
kogito/evaluation/cider/__init__.py
kogito/evaluation/cider/cider.py
kogito/evaluation/cider/cider_scorer.py
kogito/evaluation/eval.py
kogito/evaluation/meteor/__init__.py
kogito/evaluation/meteor/meteor.py
kogito/evaluation/rouge/__init__.py
kogito/evaluation/rouge/rouge.py
kogito/inference.py
kogito/models/__init__.py
kogito/models/bart/__init__.py
kogito/models/bart/comet.py
kogito/models/bart/config.py
kogito/models/bart/utils.py
kogito/models/gpt2/__init__.py
kogito/models/gpt2/comet.py
kogito/models/gpt2/utils.py
kogito/models/gpt2/zeroshot.py
kogito/models/gpt3/zeroshot.py
kogito-0.3.4.dist-info/LICENSE
kogito-0.3.4.dist-info/WHEEL
kogito-0.3.4.dist-info/METADATA
kogito-0.3.4.dist-info/RECORD
